trace_updater/TraceUpdater.py
trace_updater/__init__.py
trace_updater/_imports_.py
trace_updater/metadata.json
trace_updater/package-info.json
trace_updater/trace_updater.min.js
trace_updater/trace_updater.min.js.map
trace_updater-0.0.9.1.dist-info/LICENSE
trace_updater-0.0.9.1.dist-info/METADATA
trace_updater-0.0.9.1.dist-info/WHEEL
trace_updater-0.0.9.1.dist-info/top_level.txt
trace_updater-0.0.9.1.dist-info/RECORD
